dnstrace/__init__.py
dnstrace/__main__.py
dnstrace/_version.py
dnstrace/bpf_kprobe.c
dnstrace/bpf_sock.c
dnstrace/color.py
dnstrace/dnstrace.py
dnstrace-0.2.2.dist-info/licenses/LICENSE
dnstrace-0.2.2.dist-info/METADATA
dnstrace-0.2.2.dist-info/WHEEL
dnstrace-0.2.2.dist-info/entry_points.txt
dnstrace-0.2.2.dist-info/top_level.txt
dnstrace-0.2.2.dist-info/RECORD
