Metadata-Version: 2.4
Name: dnstrace
Version: 0.2.2
Summary: DnsTrace is a tool that identifies DNS queries made by processes on the host.
Author-email: Furkan Onder <furkanonder@protonmail.com>
Maintainer-email: Furkan Onder <furkanonder@protonmail.com>
License: MIT
Project-URL: Homepage, https://github.com/furkanonder/dnstrace
Project-URL: Documentation, https://github.com/furkanonder/dnstrace#readme
Project-URL: Repository, https://github.com/furkanonder/dnstrace.git
Project-URL: Bug Tracker, https://github.com/furkanonder/dnstrace/issues
Project-URL: Changelog, https://github.com/furkanonder/dnstrace/blob/main/CHANGELOG.md
Keywords: dns,ebpf,bpf,trace,monitoring,networking
Classifier: Development Status :: 3 - Alpha
Classifier: Intended Audience :: Developers
Classifier: Intended Audience :: System Administrators
Classifier: License :: OSI Approved :: MIT License
Classifier: Operating System :: POSIX :: Linux
Classifier: Programming Language :: Python
Classifier: Programming Language :: Python :: 3
Classifier: Programming Language :: Python :: 3 :: Only
Classifier: Programming Language :: Python :: 3.10
Classifier: Programming Language :: Python :: 3.11
Classifier: Programming Language :: Python :: 3.12
Classifier: Programming Language :: Python :: 3.13
Classifier: Topic :: System :: Monitoring
Classifier: Topic :: System :: Networking
Classifier: Topic :: System :: Systems Administration
Classifier: Topic :: Internet :: Name Service (DNS)
Classifier: Typing :: Typed
Requires-Python: >=3.10
License-File: LICENSE
Requires-Dist: dnslib>=0.9.26
Provides-Extra: dev
Requires-Dist: pytest>=8.4.2; extra == "dev"
Requires-Dist: ruff>=0.13.2; extra == "dev"
Requires-Dist: mypy>=1.18.2; extra == "dev"
Requires-Dist: pre-commit>=4.3.0; extra == "dev"
Provides-Extra: test
Requires-Dist: pytest>=8.4.2; extra == "test"
Provides-Extra: all
Requires-Dist: pytest>=8.4.2; extra == "all"
Requires-Dist: ruff>=0.13.2; extra == "all"
Requires-Dist: mypy>=1.18.2; extra == "all"
Requires-Dist: pre-commit>=4.3.0; extra == "all"
Dynamic: license-file
